{
    "code": 200,
    "desc": "成功",
    "data": {
        "list": [
            {
                "identity": 2,
                "phone": "12345678910",
                "id": 67789,
                "left_coin": 76031,
                "regtime": "2018-09-21T09:53:50+08:00",
                "invite_count": 149,
                "nickname": "用户 A",
                "avatar": "https://static.wawa.gongfutingche.com/coverkey_1533199155152"
            },
            {
                "identity": 2,
                "phone": "12345678910",
                "id": 88815,
                "left_coin": 56474,
                "regtime": "2018-09-21T09:53:50+08:00",
                "invite_count": 127,
                "nickname": "用户 C",
                "avatar": "https://static.wawa.gongfutingche.com/coverkey_1533183961469"
            },
            {
                "identity": 1,
                "phone": "12345678910",
                "id": 52712,
                "left_coin": 79970,
                "regtime": "2018-09-21T09:53:50+08:00",
                "invite_count": 186,
                "nickname": "用户 E",
                "avatar": "https://static.wawa.gongfutingche.com/coverkey_1533199155152"
            },
            {
                "identity": 2,
                "phone": "12345678910",
                "id": 75067,
                "left_coin": 74031,
                "regtime": "2018-09-21T09:53:50+08:00",
                "invite_count": 120,
                "nickname": "用户 E",
                "avatar": "https://static.wawa.gongfutingche.com/coverkey_1532695544759"
            },
            {
                "identity": 1,
                "phone": "12345678910",
                "id": 90568,
                "left_coin": 62466,
                "regtime": "2018-09-21T09:53:50+08:00",
                "invite_count": 199,
                "nickname": "用户 D",
                "avatar": "https://static.wawa.gongfutingche.com/coverkey_1533199155152"
            },
            {
                "identity": 2,
                "phone": "12345678910",
                "id": 65570,
                "left_coin": 34843,
                "regtime": "2018-09-21T09:53:50+08:00",
                "invite_count": 143,
                "nickname": "用户 D",
                "avatar": "https://static.wawa.gongfutingche.com/coverkey_1532695544759"
            },
            {
                "identity": 1,
                "phone": "12345678910",
                "id": 21162,
                "left_coin": 52232,
                "regtime": "2018-09-21T09:53:50+08:00",
                "invite_count": 72,
                "nickname": "用户 C",
                "avatar": "https://static.wawa.gongfutingche.com/coverkey_1532695544759"
            },
            {
                "identity": 1,
                "phone": "12345678910",
                "id": 33236,
                "left_coin": 14296,
                "regtime": "2018-09-21T09:53:50+08:00",
                "invite_count": 119,
                "nickname": "用户 C",
                "avatar": "https://static.wawa.gongfutingche.com/coverkey_1532695544759"
            },
            {
                "identity": 1,
                "phone": "12345678910",
                "id": 81893,
                "left_coin": 77142,
                "regtime": "2018-09-21T09:53:50+08:00",
                "invite_count": 120,
                "nickname": "用户 C",
                "avatar": "https://static.wawa.gongfutingche.com/coverkey_1533695105624"
            },
            {
                "identity": 2,
                "phone": "12345678910",
                "id": 90046,
                "left_coin": 11379,
                "regtime": "2018-09-21T09:53:50+08:00",
                "invite_count": 83,
                "nickname": "用户 C",
                "avatar": "https://static.wawa.gongfutingche.com/coverkey_1533199155152"
            }
        ],
        "count": 50
    }
}